djb/__init__.py
djb/_version.py
djb/types.py
djb/buildpacks/__init__.py
djb/buildpacks/base.py
djb/buildpacks/constants.py
djb/buildpacks/local.py
djb/buildpacks/metadata.py
djb/buildpacks/remote.py
djb/buildpacks/resolvers.py
djb/buildpacks/specs.py
djb/buildpacks/tests/__init__.py
djb/buildpacks/tests/conftest.py
djb/buildpacks/tests/test_base.py
djb/buildpacks/tests/test_local.py
djb/buildpacks/tests/test_remote.py
djb/buildpacks/tests/test_resolvers.py
djb/buildpacks/tests/test_specs.py
djb/buildpacks/tests/e2e/__init__.py
djb/buildpacks/tests/e2e/conftest.py
djb/buildpacks/tests/e2e/test_base_chain.py
djb/buildpacks/tests/e2e/test_local_chain.py
djb/buildpacks/tests/e2e/test_remote_chain.py
djb/buildpacks/tests/e2e/test_resolvers.py
djb/cli/__init__.py
djb/cli/config_cmd.py
djb/cli/context.py
djb/cli/db.py
djb/cli/dependencies.py
djb/cli/deploy.py
djb/cli/deploy_seed.py
djb/cli/deploy_superuser.py
djb/cli/djb.py
djb/cli/docker.py
djb/cli/docs_check.py
djb/cli/domain.py
djb/cli/editable.py
djb/cli/editable_stash.py
djb/cli/epilog.py
djb/cli/find_overlap.py
djb/cli/health.py
djb/cli/health_barrels.py
djb/cli/index.py
djb/cli/index_fixtures.py
djb/cli/indexer.py
djb/cli/lazy.py
djb/cli/publish.py
djb/cli/run.py
djb/cli/secrets.py
djb/cli/seed.py
djb/cli/superuser.py
djb/cli/heroku/__init__.py
djb/cli/heroku/heroku.py
djb/cli/init/__init__.py
djb/cli/init/config.py
djb/cli/init/db.py
djb/cli/init/deps.py
djb/cli/init/docker.py
djb/cli/init/hooks.py
djb/cli/init/init.py
djb/cli/init/project.py
djb/cli/init/secrets.py
djb/cli/init/shared.py
djb/cli/k8s/__init__.py
djb/cli/k8s/buildpack.py
djb/cli/k8s/constants.py
djb/cli/k8s/deploy.py
djb/cli/k8s/k8s.py
djb/cli/k8s/local.py
djb/cli/k8s/materialize.py
djb/cli/k8s/terraform.py
djb/cli/k8s/tests/__init__.py
djb/cli/k8s/tests/conftest.py
djb/cli/k8s/tests/test_commands.py
djb/cli/k8s/tests/e2e/__init__.py
djb/cli/k8s/tests/e2e/conftest.py
djb/cli/k8s/tests/e2e/test_dockerfile.py
djb/cli/k8s/tests/e2e/test_k8s.py
djb-0.2.37.dist-info/licenses/LICENSE
djb-0.2.37.dist-info/METADATA
djb-0.2.37.dist-info/WHEEL
djb-0.2.37.dist-info/entry_points.txt
djb-0.2.37.dist-info/top_level.txt
djb-0.2.37.dist-info/RECORD
