Metadata-Version: 2.4
Name: djb
Version: 0.2.37
Summary: Django + Bun deployment platform
Author: kajicom
License-Expression: MIT
Project-URL: Homepage, https://github.com/kajicom/djb
Project-URL: Repository, https://github.com/kajicom/djb
Requires-Python: >=3.14
License-File: LICENSE
Requires-Dist: django>=6.0.0
Requires-Dist: click>=8.1.8
Requires-Dist: cryptography>=44.0.0
Requires-Dist: filelock>=3.11
Requires-Dist: hcloud>=2.0.0
Requires-Dist: jinja2>=3.1.0
Requires-Dist: pyyaml>=6.0.2
Requires-Dist: requests>=2.32.0
Requires-Dist: attrs>=25.4.0
Requires-Dist: tomlkit>=0.13.0
Dynamic: license-file
